txtsearch/__init__.py
txtsearch/main.py
txtsearch-0.2.dist-info/METADATA
txtsearch-0.2.dist-info/WHEEL
txtsearch-0.2.dist-info/top_level.txt
txtsearch-0.2.dist-info/RECORD
