Metadata-Version: 2.1
Name: txtsearch
Version: 0.2
Summary: This is a library for finding keywords in text files.
Home-page: https://github.com/FLOVVI/txtsearch
Author: flovvi
Author-email: flovvi78@gmail.com
License: UNKNOWN
Project-URL: GitHub, https://github.com/FLOVVI
Keywords: search txt files txtfiles txtsearch
Platform: UNKNOWN
Classifier: Programming Language :: Python :: 3.9
Classifier: License :: OSI Approved :: MIT License
Classifier: Operating System :: OS Independent
Requires-Python: >=3.6
Requires-Dist: requests (>=2.25.1)
